clean_pandas/__init__.py
clean_pandas/clean_pandas.py
tests/__init__.py
tests/test_clean_pandas.py
clean_pandas-1.0.0.dist-info/LICENSE
clean_pandas-1.0.0.dist-info/METADATA
clean_pandas-1.0.0.dist-info/WHEEL
clean_pandas-1.0.0.dist-info/top_level.txt
clean_pandas-1.0.0.dist-info/RECORD
