Metadata-Version: 2.1
Name: clean-pandas
Version: 1.0.0
Summary: Pandas accessor for replacing, removing, or encrypting a DataFrame or Series that contains Personally Identifiable Information (PII) or Protected Health Information (PHI)
Home-page: https://github.com/awburgess/clean_pandas
Author: Aaron Burgess
Author-email: geoburge@gmail.com
License: MIT License
Platform: UNKNOWN
Classifier: Programming Language :: Python :: 3
Classifier: License :: OSI Approved :: MIT License
Classifier: Operating System :: OS Independent
Requires-Dist: Faker
Requires-Dist: cryptography
Requires-Dist: scrubadub
